setup.cfg
setup.py
bin/cellom2tif
cellom2tif/__init__.py
cellom2tif/cellom2tif.py
cellom2tif/filetypes.py
cellom2tif/tifffile.py
cellom2tif.egg-info/PKG-INFO
cellom2tif.egg-info/SOURCES.txt
cellom2tif.egg-info/dependency_links.txt
cellom2tif.egg-info/top_level.txt