Metadata-Version: 1.0
Name: cellom2tif
Version: 0.2.0
Summary: Convert Cellomics images to TIFF.
Home-page: https://github.com/jni/cellom2tif
Author: Juan Nunez-Iglesias
Author-email: juan.n@unimelb.edu.au
License: BSD 3-clause
Platform: UNKNOWN
